eventer.py
setup.py
eventer.egg-info/PKG-INFO
eventer.egg-info/SOURCES.txt
eventer.egg-info/dependency_links.txt
eventer.egg-info/top_level.txt