Metadata-Version: 1.0
Name: eventer
Version: 0.1.1
Summary: A simple event dispatching library
Home-page: UNKNOWN
Author: Anand Chitipothu
Author-email: anand@archive.org
License: GPL v3
Platform: UNKNOWN
